<?xml version="1.0" encoding="utf-8" ?>
<dwsync>
<file name="create.php" server="www.dmedia.zju.edu.cn" local="130496970646631750" remote="130496966400000000" Dst="0" />
<file name="index.php" server="www.dmedia.zju.edu.cn" local="130494638774250101" remote="130494634800000000" Dst="0" />
<file name="personal.php" server="www.dmedia.zju.edu.cn" local="130494375068249015" remote="130494370800000000" Dst="0" />
<file name="msg.php" server="www.dmedia.zju.edu.cn" local="130470544200000000" remote="130470544200000000" Dst="0" />
<file name="notice.html" server="www.dmedia.zju.edu.cn" local="130452297883388621" remote="130452295800000000" Dst="0" />
<file name="YunForm网站结构.jpg" server="www.dmedia.zju.edu.cn" local="130470544200000000" remote="130470544200000000" Dst="0" />
<file name="manage.php" server="www.dmedia.zju.edu.cn" local="130490960339648449" remote="130490955600000000" Dst="0" />
<file name="form.php" server="www.dmedia.zju.edu.cn" local="130470544200000000" remote="130470544200000000" Dst="0" />
<file name="log.txt" server="www.dmedia.zju.edu.cn" local="130494596899355456" remote="130494592200000000" Dst="0" />
<file name="elements.php" server="www.dmedia.zju.edu.cn" local="130465129748208747" remote="130470505800000000" Dst="0" />
<file name="common.php" server="www.dmedia.zju.edu.cn" local="130470544200000000" remote="130470544200000000" Dst="0" />
<file name="logout.php" server="www.dmedia.zju.edu.cn" local="130470544200000000" remote="130470544200000000" Dst="0" />
<file name="register.php" server="www.dmedia.zju.edu.cn" local="130470544200000000" remote="130470544200000000" Dst="0" />
</dwsync>